LICENSE
README.md
setup.py
chatharuhi/BaiChuan2GPT.py
chatharuhi/BaiChuanAPIGPT.py
chatharuhi/BaseDB.py
chatharuhi/BaseLLM.py
chatharuhi/ChatGLM2GPT.py
chatharuhi/ChatHaruhi.py
chatharuhi/ChatHaruhi_safe.py
chatharuhi/ChromaDB.py
chatharuhi/ErnieGPT.py
chatharuhi/GLMPro.py
chatharuhi/LangChainGPT.py
chatharuhi/NaiveDB.py
chatharuhi/PrintLLM.py
chatharuhi/Qwen118k2GPT.py
chatharuhi/SparkApi.py
chatharuhi/SparkGPT.py
chatharuhi/__init__.py
chatharuhi/role_name_to_file.py
chatharuhi/utils.py
chatharuhi.egg-info/PKG-INFO
chatharuhi.egg-info/SOURCES.txt
chatharuhi.egg-info/dependency_links.txt
chatharuhi.egg-info/top_level.txt