Metadata-Version: 2.1
Name: chatharuhi
Version: 1.0.9
Summary: A language model that imitates the tone, personality and plot of characters like Haruhi Suzumiya to chat in a similar style.
Author: Cheng Li, Weishi Mi
Author-email: chengli.thu@gmail.com, mws22@mails.tsinghua.edu.cn
Keywords: python,chatbot,LLM,role-playing,chromadb,luotuo
Classifier: Intended Audience :: Information Technology
Classifier: Natural Language :: English
Classifier: Natural Language :: Chinese (Simplified)
Classifier: Programming Language :: Python :: 3
Classifier: Operating System :: Unix
Classifier: Operating System :: MacOS :: MacOS X
Classifier: Operating System :: Microsoft :: Windows
License-File: LICENSE
